setup.py
ideone/__init__.py
ideone.egg-info/PKG-INFO
ideone.egg-info/SOURCES.txt
ideone.egg-info/dependency_links.txt
ideone.egg-info/requires.txt
ideone.egg-info/top_level.txt