Metadata-Version: 1.0
Name: ideone
Version: 0.1.0
Summary: A Python binding to the Ideone (Online Compiler) API.
Home-page: http://github.com/jschaf/ideone-api/
Author: Joe Schafer
Author-email: joe@jschaf.com
License: BSD
Keywords: API,ideone,codepad
Platform: any
Classifier: Development Status :: 3 - Alpha
Classifier: Topic :: Utilities
Classifier: License :: OSI Approved :: BSD License
